dict2class/__init__.py
dict2class/models.py
dict2class-0.1.0.dist-info/LICENSE
dict2class-0.1.0.dist-info/METADATA
dict2class-0.1.0.dist-info/WHEEL
dict2class-0.1.0.dist-info/top_level.txt
dict2class-0.1.0.dist-info/RECORD
