Metadata-Version: 2.1
Name: dict2class
Version: 0.1.0
Summary: UNKNOWN
Home-page: https://github.com/pypa/sampleproject
Author: Brennen Herbruck
Author-email: brennen.herbruck@gmail.com
License: MIT
Platform: UNKNOWN
Requires-Python: >=3.6
